<?xml version="1.0" encoding="utf-8"?>
<annotation>
<folder>images</folder>
<filename>20601a56-awake.ee92c994-6baf-11ed-9536-fc4482a2ef62.jpg</filename>
<source>
<database>MyDatabase</database>
<annotation>COCO2017</annotation>
<image>flickr</image>
<flickrid>NULL</flickrid>
<annotator>1</annotator>
</source>
<owner>
<flickrid>NULL</flickrid>
<name>Label Studio</name>
</owner>
<size>
<width>640</width>
<height>480</height>
<depth>3</depth>
</size>
<segmented>0</segmented>
<object>
<name>Awake</name>
<pose>Unspecified</pose>
<truncated>0</truncated>
<difficult>0</difficult>
<bndbox>
<xmin>251</xmin>
<ymin>154</ymin>
<xmax>490</xmax>
<ymax>468</ymax>
</bndbox>
</object>
</annotation>
